README.md
setup.py
silver_captcha/__init__.py
silver_captcha/captcha.py
silver_captcha/utils.py
silver_captcha.egg-info/PKG-INFO
silver_captcha.egg-info/SOURCES.txt
silver_captcha.egg-info/dependency_links.txt
silver_captcha.egg-info/not-zip-safe
silver_captcha.egg-info/top_level.txt