Metadata-Version: 1.0
Name: silver-captcha
Version: 1.0
Summary: Generates captcha
Home-page: http://github.com/storborg/funniest
Author: silvermoon
Author-email: faith.frontiers@gmail.com
License: MIT
Platform: UNKNOWN
